{"id":"cronodes","symbol":"crn","name":"CroNodes","asset_platform_id":"cronos","platforms":{"cronos":"0x8174bac1453c3ac7caed909c20ceadeb5e1cda00"},"detail_platforms":{"cronos":{"decimal_place":18,"contract_address":"0x8174bac1453c3ac7caed909c20ceadeb5e1cda00"}},"block_time_in_minutes":0,"hashing_algorithm":null,"categories":["Cronos Ecosystem"],"public_notice":null,"additional_notices":[],"localization":{"en":"CroNodes","de":"CroNodes","es":"CroNodes","fr":"CroNodes","it":"CroNodes","pl":"CroNodes","ro":"CroNodes","hu":"CroNodes","nl":"CroNodes","pt":"CroNodes","sv":"CroNodes","vi":"CroNodes","tr":"CroNodes","ru":"CroNodes","ja":"CroNodes","zh":"CroNodes","zh-tw":"CroNodes","ko":"CroNodes","ar":"CroNodes","th":"CroNodes","id":"CroNodes","cs":"CroNodes","da":"CroNodes","el":"CroNodes","hi":"CroNodes","no":"CroNodes","sk":"CroNodes","uk":"CroNodes","he":"CroNodes","fi":"CroNodes","bg":"CroNodes","hr":"CroNodes","lt":"CroNodes","sl":"CroNodes"},"description":{"en":"CRN is the native token required to create a node through the Cronodes protocol.","de":"CRN is the native token required to create a node through the Cronodes protocol.","es":"CRN is the native token required to create a node through the Cronodes protocol.","fr":"CRN is the native token required to create a node through the Cronodes protocol.","it":"CRN is the native token required to create a node through the Cronodes protocol.","pl":"CRN is the native token required to create a node through the Cronodes protocol.","ro":"CRN is the native token required to create a node through the Cronodes protocol.","hu":"CRN is the native token required to create a node through the Cronodes protocol.","nl":"CRN is the native token required to create a node through the Cronodes protocol.","pt":"CRN is the native token required to create a node through the Cronodes protocol.","sv":"CRN is the native token required to create a node through the Cronodes protocol.","vi":"CRN is the native token required to create a node through the Cronodes protocol.","tr":"CRN is the native token required to create a node through the Cronodes protocol.","ru":"CRN is the native token required to create a node through the Cronodes protocol.","ja":"CRN is the native token required to create a node through the Cronodes protocol.","zh":"CRN is the native token required to create a node through the Cronodes protocol.","zh-tw":"CRN is the native token required to create a node through the Cronodes protocol.","ko":"CRN is the native token required to create a node through the Cronodes protocol.","ar":"CRN is the native token required to create a node through the Cronodes protocol.","th":"CRN is the native token required to create a node through the Cronodes protocol.","id":"CRN is the native token required to create a node through the Cronodes protocol.","cs":"CRN is the native token required to create a node through the Cronodes protocol.","da":"CRN is the native token required to create a node through the Cronodes protocol.","el":"CRN is the native token required to create a node through the Cronodes protocol.","hi":"CRN is the native token required to create a node through the Cronodes protocol.","no":"CRN is the native token required to create a node through the Cronodes protocol.","sk":"CRN is the native token required to create a node through the Cronodes protocol.","uk":"CRN is the native token required to create a node through the Cronodes protocol.","he":"CRN is the native token required to create a node through the Cronodes protocol.","fi":"CRN is the native token required to create a node through the Cronodes protocol.","bg":"CRN is the native token required to create a node through the Cronodes protocol.","hr":"CRN is the native token required to create a node through the Cronodes protocol.","lt":"CRN is the native token required to create a node through the Cronodes protocol.","sl":"CRN is the native token required to create a node through the Cronodes protocol."},"links":{"homepage":["https://www.cronodes.xyz/","",""],"blockchain_site":["https://cronos.crypto.org/explorer/token/0x8174BaC1453c3AC7CaED909c20ceaDeb5E1CDA00/token-transfers","https://cronos-explorer.crypto.org/token/0x8174BaC1453c3AC7CaED909c20ceaDeb5E1CDA00","","","","","","","",""],"official_forum_url":["","",""],"chat_url":["https://discord.com/invite/jZe366FaP5","",""],"announcement_url":["",""],"twitter_screen_name":"CronodesFinance","facebook_username":"","bitcointalk_thread_identifier":null,"telegram_channel_identifier":"","subreddit_url":null,"repos_url":{"github":[],"bitbucket":[]}},"image":{"thumb":"https://assets.coingecko.com/coins/images/22548/thumb/Zy4D1gfB_400x400.jpg?1642051190","small":"https://assets.coingecko.com/coins/images/22548/small/Zy4D1gfB_400x400.jpg?1642051190","large":"https://assets.coingecko.com/coins/images/22548/large/Zy4D1gfB_400x400.jpg?1642051190"},"country_origin":"","genesis_date":null,"contract_address":"0x8174bac1453c3ac7caed909c20ceadeb5e1cda00","sentiment_votes_up_percentage":0,"sentiment_votes_down_percentage":100,"watchlist_portfolio_users":4903,"market_cap_rank":null,"coingecko_rank":5732,"coingecko_score":1.979,"developer_score":0,"community_score":8.087,"liquidity_score":1,"public_interest_score":0,"public_interest_stats":{"alexa_rank":null,"bing_matches":null},"status_updates":[],"last_updated":"2023-07-04T09:51:15.139Z"}