{"id":"omax-token","symbol":"omax","name":"Omax","asset_platform_id":null,"platforms":{"":""},"detail_platforms":{"":{"decimal_place":null,"contract_address":""}},"block_time_in_minutes":0,"hashing_algorithm":null,"categories":[],"public_notice":"OMAX has migrated from the <a href=\"https://bscscan.com/token/0xeB84be66c8E71f07eA57Cf3b21626d7784F32A7F\">old BSC contract</a> to <a href=\"https://omaxray.com/\">its native mainnet</a>.","additional_notices":[],"localization":{"en":"Omax","de":"Omax","es":"Omax","fr":"Omax","it":"Omax","pl":"Omax","ro":"Omax","hu":"Omax","nl":"Omax","pt":"Omax","sv":"Omax","vi":"Omax","tr":"Omax","ru":"Omax","ja":"Omax","zh":"Omax","zh-tw":"Omax","ko":"Omax","ar":"Omax","th":"Omax","id":"Omax","cs":"Omax","da":"Omax","el":"Omax","hi":"Omax","no":"Omax","sk":"Omax","uk":"Omax","he":"Omax","fi":"Omax","bg":"Omax","hr":"Omax","lt":"Omax","sl":"Omax"},"description":{"en":"What Is OMAX TOKEN (OMAX)?\r\nOMAX is a community-driven token which was launched on 3rd of November 2021 in binance network  with the\r\nintention to have its own blockchain to educate the next\r\ngeneration of investors and make crypto simple and safe for everyone.\r\n\r\nOMAX is one of the fastest growing projects which is\r\nmoving from BEP20 to their own network (blockchain\r\nOMX20) which is also a EVM compatible. It is way ahead of the roadmaps and the blockchain is already on testnet and open for public testing with 67K TPS with estimated 85K+\r\nTPS on mainnet. Omax testnet was launched on 3rd of April 2022. OMAX  mainnet is scheduled to launch by the end of\r\nJuly 2022.\r\n\r\nIt further plans to launch a marketing campaign on Twitter\r\nto raise awareness and reach 100,000 holders. That will\r\nlikely go hand in hand with launching of their blockchain.\r\nOMAX was advertised in Times square NY and famous\r\ncelebrities promoted across the globe. Promotion videos\r\ncan be found in the social media.\r\n\r\nWhat Makes OMAX Unique?\r\nIn contrast to many other coins, OMAX promises to feature a complete ecosystem that gives its token real value. Its\r\nblockchain, Ecommerce integration, Crypto card.\r\nBy integrating the Blockchain into popular e-commerce and shopping cart platforms, OMAX aim to grant users the\r\nability to easily complete their everyday purchases using\r\ntheir crypto currency balances.\r\n\r\nOMAX is headquartered in DUBAI, UAE because of its\r\nfriendly crypto law. The developers  are from Australia and United Kingdom. They have a plan to launch the OMAX\r\nexchange in early 2023.\r\n\r\n\r\nHow Many OMAX Tokens (OMAX) are there in Circulation?\r\nOMAX has a total supply of 10 billion tokens. 4% of that was already burned. In addition, OMAX follows the patented\r\napproach of deflationary tokens by burning 4% of each\r\ntoken at a BUY&SELL transaction. Doing that, the team\r\nwants to constantly shrink the existing token supply and\r\nincrease the value of OMAX.\r\n\r\n\r\nHow Is the OMAX (OMX 20) Network secured?\r\nOMAX Chain relies on a system of PoS consensus that can support short block time and lower fees. The most bonded validator candidates of staking will become validators and\r\nproduce blocks. The double sign detection and other\r\nslashing logic guarantee security, stability, and chain\r\nfinality. The OMAX Chain also supports EVM-compatible\r\nsmart contracts and protocols. This is the native and only\r\nusable currency in the OMAX ecosystem.","de":"What Is OMAX TOKEN (OMAX)?\r\nOMAX is a community-driven token which was launched on 3rd of November 2021 in binance network  with the\r\nintention to have its own blockchain to educate the next\r\ngeneration of investors and make crypto simple and safe for everyone.\r\n\r\nOMAX is one of the fastest growing projects which is\r\nmoving from BEP20 to their own network (blockchain\r\nOMX20) which is also a EVM compatible. It is way ahead of the roadmaps and the blockchain is already on testnet and open for public testing with 67K TPS with estimated 85K+\r\nTPS on mainnet. Omax testnet was launched on 3rd of April 2022. OMAX  mainnet is scheduled to launch by the end of\r\nJuly 2022.\r\n\r\nIt further plans to launch a marketing campaign on Twitter\r\nto raise awareness and reach 100,000 holders. That will\r\nlikely go hand in hand with launching of their blockchain.\r\nOMAX was advertised in Times square NY and famous\r\ncelebrities promoted across the globe. Promotion videos\r\ncan be found in the social media.\r\n\r\nWhat Makes OMAX Unique?\r\nIn contrast to many other coins, OMAX promises to feature a complete ecosystem that gives its token real value. Its\r\nblockchain, Ecommerce integration, Crypto card.\r\nBy integrating the Blockchain into popular e-commerce and shopping cart platforms, OMAX aim to grant users the\r\nability to easily complete their everyday purchases using\r\ntheir crypto currency balances.\r\n\r\nOMAX is headquartered in DUBAI, UAE because of its\r\nfriendly crypto law. The developers  are from Australia and United Kingdom. They have a plan to launch the OMAX\r\nexchange in early 2023.\r\n\r\n\r\nHow Many OMAX Tokens (OMAX) are there in Circulation?\r\nOMAX has a total supply of 10 billion tokens. 4% of that was already burned. In addition, OMAX follows the patented\r\napproach of deflationary tokens by burning 4% of each\r\ntoken at a BUY&SELL transaction. Doing that, the team\r\nwants to constantly shrink the existing token supply and\r\nincrease the value of OMAX.\r\n\r\n\r\nHow Is the OMAX (OMX 20) Network secured?\r\nOMAX Chain relies on a system of PoS consensus that can support short block time and lower fees. The most bonded validator candidates of staking will become validators and\r\nproduce blocks. The double sign detection and other\r\nslashing logic guarantee security, stability, and chain\r\nfinality. The OMAX Chain also supports EVM-compatible\r\nsmart contracts and protocols. This is the native and only\r\nusable currency in the OMAX ecosystem.","es":"What Is OMAX TOKEN (OMAX)?\r\nOMAX is a community-driven token which was launched on 3rd of November 2021 in binance network  with the\r\nintention to have its own blockchain to educate the next\r\ngeneration of investors and make crypto simple and safe for everyone.\r\n\r\nOMAX is one of the fastest growing projects which is\r\nmoving from BEP20 to their own network (blockchain\r\nOMX20) which is also a EVM compatible. It is way ahead of the roadmaps and the blockchain is already on testnet and open for public testing with 67K TPS with estimated 85K+\r\nTPS on mainnet. Omax testnet was launched on 3rd of April 2022. OMAX  mainnet is scheduled to launch by the end of\r\nJuly 2022.\r\n\r\nIt further plans to launch a marketing campaign on Twitter\r\nto raise awareness and reach 100,000 holders. That will\r\nlikely go hand in hand with launching of their blockchain.\r\nOMAX was advertised in Times square NY and famous\r\ncelebrities promoted across the globe. Promotion videos\r\ncan be found in the social media.\r\n\r\nWhat Makes OMAX Unique?\r\nIn contrast to many other coins, OMAX promises to feature a complete ecosystem that gives its token real value. Its\r\nblockchain, Ecommerce integration, Crypto card.\r\nBy integrating the Blockchain into popular e-commerce and shopping cart platforms, OMAX aim to grant users the\r\nability to easily complete their everyday purchases using\r\ntheir crypto currency balances.\r\n\r\nOMAX is headquartered in DUBAI, UAE because of its\r\nfriendly crypto law. The developers  are from Australia and United Kingdom. They have a plan to launch the OMAX\r\nexchange in early 2023.\r\n\r\n\r\nHow Many OMAX Tokens (OMAX) are there in Circulation?\r\nOMAX has a total supply of 10 billion tokens. 4% of that was already burned. In addition, OMAX follows the patented\r\napproach of deflationary tokens by burning 4% of each\r\ntoken at a BUY&SELL transaction. Doing that, the team\r\nwants to constantly shrink the existing token supply and\r\nincrease the value of OMAX.\r\n\r\n\r\nHow Is the OMAX (OMX 20) Network secured?\r\nOMAX Chain relies on a system of PoS consensus that can support short block time and lower fees. The most bonded validator candidates of staking will become validators and\r\nproduce blocks. The double sign detection and other\r\nslashing logic guarantee security, stability, and chain\r\nfinality. The OMAX Chain also supports EVM-compatible\r\nsmart contracts and protocols. This is the native and only\r\nusable currency in the OMAX ecosystem.","fr":"What Is OMAX TOKEN (OMAX)?\r\nOMAX is a community-driven token which was launched on 3rd of November 2021 in binance network  with the\r\nintention to have its own blockchain to educate the next\r\ngeneration of investors and make crypto simple and safe for everyone.\r\n\r\nOMAX is one of the fastest growing projects which is\r\nmoving from BEP20 to their own network (blockchain\r\nOMX20) which is also a EVM compatible. It is way ahead of the roadmaps and the blockchain is already on testnet and open for public testing with 67K TPS with estimated 85K+\r\nTPS on mainnet. Omax testnet was launched on 3rd of April 2022. OMAX  mainnet is scheduled to launch by the end of\r\nJuly 2022.\r\n\r\nIt further plans to launch a marketing campaign on Twitter\r\nto raise awareness and reach 100,000 holders. That will\r\nlikely go hand in hand with launching of their blockchain.\r\nOMAX was advertised in Times square NY and famous\r\ncelebrities promoted across the globe. Promotion videos\r\ncan be found in the social media.\r\n\r\nWhat Makes OMAX Unique?\r\nIn contrast to many other coins, OMAX promises to feature a complete ecosystem that gives its token real value. Its\r\nblockchain, Ecommerce integration, Crypto card.\r\nBy integrating the Blockchain into popular e-commerce and shopping cart platforms, OMAX aim to grant users the\r\nability to easily complete their everyday purchases using\r\ntheir crypto currency balances.\r\n\r\nOMAX is headquartered in DUBAI, UAE because of its\r\nfriendly crypto law. The developers  are from Australia and United Kingdom. They have a plan to launch the OMAX\r\nexchange in early 2023.\r\n\r\n\r\nHow Many OMAX Tokens (OMAX) are there in Circulation?\r\nOMAX has a total supply of 10 billion tokens. 4% of that was already burned. In addition, OMAX follows the patented\r\napproach of deflationary tokens by burning 4% of each\r\ntoken at a BUY&SELL transaction. Doing that, the team\r\nwants to constantly shrink the existing token supply and\r\nincrease the value of OMAX.\r\n\r\n\r\nHow Is the OMAX (OMX 20) Network secured?\r\nOMAX Chain relies on a system of PoS consensus that can support short block time and lower fees. The most bonded validator candidates of staking will become validators and\r\nproduce blocks. The double sign detection and other\r\nslashing logic guarantee security, stability, and chain\r\nfinality. The OMAX Chain also supports EVM-compatible\r\nsmart contracts and protocols. This is the native and only\r\nusable currency in the OMAX ecosystem.","it":"What Is OMAX TOKEN (OMAX)?\r\nOMAX is a community-driven token which was launched on 3rd of November 2021 in binance network  with the\r\nintention to have its own blockchain to educate the next\r\ngeneration of investors and make crypto simple and safe for everyone.\r\n\r\nOMAX is one of the fastest growing projects which is\r\nmoving from BEP20 to their own network (blockchain\r\nOMX20) which is also a EVM compatible. It is way ahead of the roadmaps and the blockchain is already on testnet and open for public testing with 67K TPS with estimated 85K+\r\nTPS on mainnet. Omax testnet was launched on 3rd of April 2022. OMAX  mainnet is scheduled to launch by the end of\r\nJuly 2022.\r\n\r\nIt further plans to launch a marketing campaign on Twitter\r\nto raise awareness and reach 100,000 holders. That will\r\nlikely go hand in hand with launching of their blockchain.\r\nOMAX was advertised in Times square NY and famous\r\ncelebrities promoted across the globe. Promotion videos\r\ncan be found in the social media.\r\n\r\nWhat Makes OMAX Unique?\r\nIn contrast to many other coins, OMAX promises to feature a complete ecosystem that gives its token real value. Its\r\nblockchain, Ecommerce integration, Crypto card.\r\nBy integrating the Blockchain into popular e-commerce and shopping cart platforms, OMAX aim to grant users the\r\nability to easily complete their everyday purchases using\r\ntheir crypto currency balances.\r\n\r\nOMAX is headquartered in DUBAI, UAE because of its\r\nfriendly crypto law. The developers  are from Australia and United Kingdom. They have a plan to launch the OMAX\r\nexchange in early 2023.\r\n\r\n\r\nHow Many OMAX Tokens (OMAX) are there in Circulation?\r\nOMAX has a total supply of 10 billion tokens. 4% of that was already burned. In addition, OMAX follows the patented\r\napproach of deflationary tokens by burning 4% of each\r\ntoken at a BUY&SELL transaction. Doing that, the team\r\nwants to constantly shrink the existing token supply and\r\nincrease the value of OMAX.\r\n\r\n\r\nHow Is the OMAX (OMX 20) Network secured?\r\nOMAX Chain relies on a system of PoS consensus that can support short block time and lower fees. The most bonded validator candidates of staking will become validators and\r\nproduce blocks. The double sign detection and other\r\nslashing logic guarantee security, stability, and chain\r\nfinality. The OMAX Chain also supports EVM-compatible\r\nsmart contracts and protocols. This is the native and only\r\nusable currency in the OMAX ecosystem.","pl":"What Is OMAX TOKEN (OMAX)?\r\nOMAX is a community-driven token which was launched on 3rd of November 2021 in binance network  with the\r\nintention to have its own blockchain to educate the next\r\ngeneration of investors and make crypto simple and safe for everyone.\r\n\r\nOMAX is one of the fastest growing projects which is\r\nmoving from BEP20 to their own network (blockchain\r\nOMX20) which is also a EVM compatible. It is way ahead of the roadmaps and the blockchain is already on testnet and open for public testing with 67K TPS with estimated 85K+\r\nTPS on mainnet. Omax testnet was launched on 3rd of April 2022. OMAX  mainnet is scheduled to launch by the end of\r\nJuly 2022.\r\n\r\nIt further plans to launch a marketing campaign on Twitter\r\nto raise awareness and reach 100,000 holders. That will\r\nlikely go hand in hand with launching of their blockchain.\r\nOMAX was advertised in Times square NY and famous\r\ncelebrities promoted across the globe. Promotion videos\r\ncan be found in the social media.\r\n\r\nWhat Makes OMAX Unique?\r\nIn contrast to many other coins, OMAX promises to feature a complete ecosystem that gives its token real value. Its\r\nblockchain, Ecommerce integration, Crypto card.\r\nBy integrating the Blockchain into popular e-commerce and shopping cart platforms, OMAX aim to grant users the\r\nability to easily complete their everyday purchases using\r\ntheir crypto currency balances.\r\n\r\nOMAX is headquartered in DUBAI, UAE because of its\r\nfriendly crypto law. The developers  are from Australia and United Kingdom. They have a plan to launch the OMAX\r\nexchange in early 2023.\r\n\r\n\r\nHow Many OMAX Tokens (OMAX) are there in Circulation?\r\nOMAX has a total supply of 10 billion tokens. 4% of that was already burned. In addition, OMAX follows the patented\r\napproach of deflationary tokens by burning 4% of each\r\ntoken at a BUY&SELL transaction. Doing that, the team\r\nwants to constantly shrink the existing token supply and\r\nincrease the value of OMAX.\r\n\r\n\r\nHow Is the OMAX (OMX 20) Network secured?\r\nOMAX Chain relies on a system of PoS consensus that can support short block time and lower fees. The most bonded validator candidates of staking will become validators and\r\nproduce blocks. The double sign detection and other\r\nslashing logic guarantee security, stability, and chain\r\nfinality. The OMAX Chain also supports EVM-compatible\r\nsmart contracts and protocols. This is the native and only\r\nusable currency in the OMAX ecosystem.","ro":"What Is OMAX TOKEN (OMAX)?\r\nOMAX is a community-driven token which was launched on 3rd of November 2021 in binance network  with the\r\nintention to have its own blockchain to educate the next\r\ngeneration of investors and make crypto simple and safe for everyone.\r\n\r\nOMAX is one of the fastest growing projects which is\r\nmoving from BEP20 to their own network (blockchain\r\nOMX20) which is also a EVM compatible. It is way ahead of the roadmaps and the blockchain is already on testnet and open for public testing with 67K TPS with estimated 85K+\r\nTPS on mainnet. Omax testnet was launched on 3rd of April 2022. OMAX  mainnet is scheduled to launch by the end of\r\nJuly 2022.\r\n\r\nIt further plans to launch a marketing campaign on Twitter\r\nto raise awareness and reach 100,000 holders. That will\r\nlikely go hand in hand with launching of their blockchain.\r\nOMAX was advertised in Times square NY and famous\r\ncelebrities promoted across the globe. Promotion videos\r\ncan be found in the social media.\r\n\r\nWhat Makes OMAX Unique?\r\nIn contrast to many other coins, OMAX promises to feature a complete ecosystem that gives its token real value. Its\r\nblockchain, Ecommerce integration, Crypto card.\r\nBy integrating the Blockchain into popular e-commerce and shopping cart platforms, OMAX aim to grant users the\r\nability to easily complete their everyday purchases using\r\ntheir crypto currency balances.\r\n\r\nOMAX is headquartered in DUBAI, UAE because of its\r\nfriendly crypto law. The developers  are from Australia and United Kingdom. They have a plan to launch the OMAX\r\nexchange in early 2023.\r\n\r\n\r\nHow Many OMAX Tokens (OMAX) are there in Circulation?\r\nOMAX has a total supply of 10 billion tokens. 4% of that was already burned. In addition, OMAX follows the patented\r\napproach of deflationary tokens by burning 4% of each\r\ntoken at a BUY&SELL transaction. Doing that, the team\r\nwants to constantly shrink the existing token supply and\r\nincrease the value of OMAX.\r\n\r\n\r\nHow Is the OMAX (OMX 20) Network secured?\r\nOMAX Chain relies on a system of PoS consensus that can support short block time and lower fees. The most bonded validator candidates of staking will become validators and\r\nproduce blocks. The double sign detection and other\r\nslashing logic guarantee security, stability, and chain\r\nfinality. The OMAX Chain also supports EVM-compatible\r\nsmart contracts and protocols. This is the native and only\r\nusable currency in the OMAX ecosystem.","hu":"What Is OMAX TOKEN (OMAX)?\r\nOMAX is a community-driven token which was launched on 3rd of November 2021 in binance network  with the\r\nintention to have its own blockchain to educate the next\r\ngeneration of investors and make crypto simple and safe for everyone.\r\n\r\nOMAX is one of the fastest growing projects which is\r\nmoving from BEP20 to their own network (blockchain\r\nOMX20) which is also a EVM compatible. It is way ahead of the roadmaps and the blockchain is already on testnet and open for public testing with 67K TPS with estimated 85K+\r\nTPS on mainnet. Omax testnet was launched on 3rd of April 2022. OMAX  mainnet is scheduled to launch by the end of\r\nJuly 2022.\r\n\r\nIt further plans to launch a marketing campaign on Twitter\r\nto raise awareness and reach 100,000 holders. That will\r\nlikely go hand in hand with launching of their blockchain.\r\nOMAX was advertised in Times square NY and famous\r\ncelebrities promoted across the globe. Promotion videos\r\ncan be found in the social media.\r\n\r\nWhat Makes OMAX Unique?\r\nIn contrast to many other coins, OMAX promises to feature a complete ecosystem that gives its token real value. Its\r\nblockchain, Ecommerce integration, Crypto card.\r\nBy integrating the Blockchain into popular e-commerce and shopping cart platforms, OMAX aim to grant users the\r\nability to easily complete their everyday purchases using\r\ntheir crypto currency balances.\r\n\r\nOMAX is headquartered in DUBAI, UAE because of its\r\nfriendly crypto law. The developers  are from Australia and United Kingdom. They have a plan to launch the OMAX\r\nexchange in early 2023.\r\n\r\n\r\nHow Many OMAX Tokens (OMAX) are there in Circulation?\r\nOMAX has a total supply of 10 billion tokens. 4% of that was already burned. In addition, OMAX follows the patented\r\napproach of deflationary tokens by burning 4% of each\r\ntoken at a BUY&SELL transaction. Doing that, the team\r\nwants to constantly shrink the existing token supply and\r\nincrease the value of OMAX.\r\n\r\n\r\nHow Is the OMAX (OMX 20) Network secured?\r\nOMAX Chain relies on a system of PoS consensus that can support short block time and lower fees. The most bonded validator candidates of staking will become validators and\r\nproduce blocks. The double sign detection and other\r\nslashing logic guarantee security, stability, and chain\r\nfinality. The OMAX Chain also supports EVM-compatible\r\nsmart contracts and protocols. This is the native and only\r\nusable currency in the OMAX ecosystem.","nl":"What Is OMAX TOKEN (OMAX)?\r\nOMAX is a community-driven token which was launched on 3rd of November 2021 in binance network  with the\r\nintention to have its own blockchain to educate the next\r\ngeneration of investors and make crypto simple and safe for everyone.\r\n\r\nOMAX is one of the fastest growing projects which is\r\nmoving from BEP20 to their own network (blockchain\r\nOMX20) which is also a EVM compatible. It is way ahead of the roadmaps and the blockchain is already on testnet and open for public testing with 67K TPS with estimated 85K+\r\nTPS on mainnet. Omax testnet was launched on 3rd of April 2022. OMAX  mainnet is scheduled to launch by the end of\r\nJuly 2022.\r\n\r\nIt further plans to launch a marketing campaign on Twitter\r\nto raise awareness and reach 100,000 holders. That will\r\nlikely go hand in hand with launching of their blockchain.\r\nOMAX was advertised in Times square NY and famous\r\ncelebrities promoted across the globe. Promotion videos\r\ncan be found in the social media.\r\n\r\nWhat Makes OMAX Unique?\r\nIn contrast to many other coins, OMAX promises to feature a complete ecosystem that gives its token real value. Its\r\nblockchain, Ecommerce integration, Crypto card.\r\nBy integrating the Blockchain into popular e-commerce and shopping cart platforms, OMAX aim to grant users the\r\nability to easily complete their everyday purchases using\r\ntheir crypto currency balances.\r\n\r\nOMAX is headquartered in DUBAI, UAE because of its\r\nfriendly crypto law. The developers  are from Australia and United Kingdom. They have a plan to launch the OMAX\r\nexchange in early 2023.\r\n\r\n\r\nHow Many OMAX Tokens (OMAX) are there in Circulation?\r\nOMAX has a total supply of 10 billion tokens. 4% of that was already burned. In addition, OMAX follows the patented\r\napproach of deflationary tokens by burning 4% of each\r\ntoken at a BUY&SELL transaction. Doing that, the team\r\nwants to constantly shrink the existing token supply and\r\nincrease the value of OMAX.\r\n\r\n\r\nHow Is the OMAX (OMX 20) Network secured?\r\nOMAX Chain relies on a system of PoS consensus that can support short block time and lower fees. The most bonded validator candidates of staking will become validators and\r\nproduce blocks. The double sign detection and other\r\nslashing logic guarantee security, stability, and chain\r\nfinality. The OMAX Chain also supports EVM-compatible\r\nsmart contracts and protocols. This is the native and only\r\nusable currency in the OMAX ecosystem.","pt":"What Is OMAX TOKEN (OMAX)?\r\nOMAX is a community-driven token which was launched on 3rd of November 2021 in binance network  with the\r\nintention to have its own blockchain to educate the next\r\ngeneration of investors and make crypto simple and safe for everyone.\r\n\r\nOMAX is one of the fastest growing projects which is\r\nmoving from BEP20 to their own network (blockchain\r\nOMX20) which is also a EVM compatible. It is way ahead of the roadmaps and the blockchain is already on testnet and open for public testing with 67K TPS with estimated 85K+\r\nTPS on mainnet. Omax testnet was launched on 3rd of April 2022. OMAX  mainnet is scheduled to launch by the end of\r\nJuly 2022.\r\n\r\nIt further plans to launch a marketing campaign on Twitter\r\nto raise awareness and reach 100,000 holders. That will\r\nlikely go hand in hand with launching of their blockchain.\r\nOMAX was advertised in Times square NY and famous\r\ncelebrities promoted across the globe. Promotion videos\r\ncan be found in the social media.\r\n\r\nWhat Makes OMAX Unique?\r\nIn contrast to many other coins, OMAX promises to feature a complete ecosystem that gives its token real value. Its\r\nblockchain, Ecommerce integration, Crypto card.\r\nBy integrating the Blockchain into popular e-commerce and shopping cart platforms, OMAX aim to grant users the\r\nability to easily complete their everyday purchases using\r\ntheir crypto currency balances.\r\n\r\nOMAX is headquartered in DUBAI, UAE because of its\r\nfriendly crypto law. The developers  are from Australia and United Kingdom. They have a plan to launch the OMAX\r\nexchange in early 2023.\r\n\r\n\r\nHow Many OMAX Tokens (OMAX) are there in Circulation?\r\nOMAX has a total supply of 10 billion tokens. 4% of that was already burned. In addition, OMAX follows the patented\r\napproach of deflationary tokens by burning 4% of each\r\ntoken at a BUY&SELL transaction. Doing that, the team\r\nwants to constantly shrink the existing token supply and\r\nincrease the value of OMAX.\r\n\r\n\r\nHow Is the OMAX (OMX 20) Network secured?\r\nOMAX Chain relies on a system of PoS consensus that can support short block time and lower fees. The most bonded validator candidates of staking will become validators and\r\nproduce blocks. The double sign detection and other\r\nslashing logic guarantee security, stability, and chain\r\nfinality. The OMAX Chain also supports EVM-compatible\r\nsmart contracts and protocols. This is the native and only\r\nusable currency in the OMAX ecosystem.","sv":"What Is OMAX TOKEN (OMAX)?\r\nOMAX is a community-driven token which was launched on 3rd of November 2021 in binance network  with the\r\nintention to have its own blockchain to educate the next\r\ngeneration of investors and make crypto simple and safe for everyone.\r\n\r\nOMAX is one of the fastest growing projects which is\r\nmoving from BEP20 to their own network (blockchain\r\nOMX20) which is also a EVM compatible. It is way ahead of the roadmaps and the blockchain is already on testnet and open for public testing with 67K TPS with estimated 85K+\r\nTPS on mainnet. Omax testnet was launched on 3rd of April 2022. OMAX  mainnet is scheduled to launch by the end of\r\nJuly 2022.\r\n\r\nIt further plans to launch a marketing campaign on Twitter\r\nto raise awareness and reach 100,000 holders. That will\r\nlikely go hand in hand with launching of their blockchain.\r\nOMAX was advertised in Times square NY and famous\r\ncelebrities promoted across the globe. Promotion videos\r\ncan be found in the social media.\r\n\r\nWhat Makes OMAX Unique?\r\nIn contrast to many other coins, OMAX promises to feature a complete ecosystem that gives its token real value. Its\r\nblockchain, Ecommerce integration, Crypto card.\r\nBy integrating the Blockchain into popular e-commerce and shopping cart platforms, OMAX aim to grant users the\r\nability to easily complete their everyday purchases using\r\ntheir crypto currency balances.\r\n\r\nOMAX is headquartered in DUBAI, UAE because of its\r\nfriendly crypto law. The developers  are from Australia and United Kingdom. They have a plan to launch the OMAX\r\nexchange in early 2023.\r\n\r\n\r\nHow Many OMAX Tokens (OMAX) are there in Circulation?\r\nOMAX has a total supply of 10 billion tokens. 4% of that was already burned. In addition, OMAX follows the patented\r\napproach of deflationary tokens by burning 4% of each\r\ntoken at a BUY&SELL transaction. Doing that, the team\r\nwants to constantly shrink the existing token supply and\r\nincrease the value of OMAX.\r\n\r\n\r\nHow Is the OMAX (OMX 20) Network secured?\r\nOMAX Chain relies on a system of PoS consensus that can support short block time and lower fees. The most bonded validator candidates of staking will become validators and\r\nproduce blocks. The double sign detection and other\r\nslashing logic guarantee security, stability, and chain\r\nfinality. The OMAX Chain also supports EVM-compatible\r\nsmart contracts and protocols. This is the native and only\r\nusable currency in the OMAX ecosystem.","vi":"What Is OMAX TOKEN (OMAX)?\r\nOMAX is a community-driven token which was launched on 3rd of November 2021 in binance network  with the\r\nintention to have its own blockchain to educate the next\r\ngeneration of investors and make crypto simple and safe for everyone.\r\n\r\nOMAX is one of the fastest growing projects which is\r\nmoving from BEP20 to their own network (blockchain\r\nOMX20) which is also a EVM compatible. It is way ahead of the roadmaps and the blockchain is already on testnet and open for public testing with 67K TPS with estimated 85K+\r\nTPS on mainnet. Omax testnet was launched on 3rd of April 2022. OMAX  mainnet is scheduled to launch by the end of\r\nJuly 2022.\r\n\r\nIt further plans to launch a marketing campaign on Twitter\r\nto raise awareness and reach 100,000 holders. That will\r\nlikely go hand in hand with launching of their blockchain.\r\nOMAX was advertised in Times square NY and famous\r\ncelebrities promoted across the globe. Promotion videos\r\ncan be found in the social media.\r\n\r\nWhat Makes OMAX Unique?\r\nIn contrast to many other coins, OMAX promises to feature a complete ecosystem that gives its token real value. Its\r\nblockchain, Ecommerce integration, Crypto card.\r\nBy integrating the Blockchain into popular e-commerce and shopping cart platforms, OMAX aim to grant users the\r\nability to easily complete their everyday purchases using\r\ntheir crypto currency balances.\r\n\r\nOMAX is headquartered in DUBAI, UAE because of its\r\nfriendly crypto law. The developers  are from Australia and United Kingdom. They have a plan to launch the OMAX\r\nexchange in early 2023.\r\n\r\n\r\nHow Many OMAX Tokens (OMAX) are there in Circulation?\r\nOMAX has a total supply of 10 billion tokens. 4% of that was already burned. In addition, OMAX follows the patented\r\napproach of deflationary tokens by burning 4% of each\r\ntoken at a BUY&SELL transaction. Doing that, the team\r\nwants to constantly shrink the existing token supply and\r\nincrease the value of OMAX.\r\n\r\n\r\nHow Is the OMAX (OMX 20) Network secured?\r\nOMAX Chain relies on a system of PoS consensus that can support short block time and lower fees. The most bonded validator candidates of staking will become validators and\r\nproduce blocks. The double sign detection and other\r\nslashing logic guarantee security, stability, and chain\r\nfinality. The OMAX Chain also supports EVM-compatible\r\nsmart contracts and protocols. This is the native and only\r\nusable currency in the OMAX ecosystem.","tr":"What Is OMAX TOKEN (OMAX)?\r\nOMAX is a community-driven token which was launched on 3rd of November 2021 in binance network  with the\r\nintention to have its own blockchain to educate the next\r\ngeneration of investors and make crypto simple and safe for everyone.\r\n\r\nOMAX is one of the fastest growing projects which is\r\nmoving from BEP20 to their own network (blockchain\r\nOMX20) which is also a EVM compatible. It is way ahead of the roadmaps and the blockchain is already on testnet and open for public testing with 67K TPS with estimated 85K+\r\nTPS on mainnet. Omax testnet was launched on 3rd of April 2022. OMAX  mainnet is scheduled to launch by the end of\r\nJuly 2022.\r\n\r\nIt further plans to launch a marketing campaign on Twitter\r\nto raise awareness and reach 100,000 holders. That will\r\nlikely go hand in hand with launching of their blockchain.\r\nOMAX was advertised in Times square NY and famous\r\ncelebrities promoted across the globe. Promotion videos\r\ncan be found in the social media.\r\n\r\nWhat Makes OMAX Unique?\r\nIn contrast to many other coins, OMAX promises to feature a complete ecosystem that gives its token real value. Its\r\nblockchain, Ecommerce integration, Crypto card.\r\nBy integrating the Blockchain into popular e-commerce and shopping cart platforms, OMAX aim to grant users the\r\nability to easily complete their everyday purchases using\r\ntheir crypto currency balances.\r\n\r\nOMAX is headquartered in DUBAI, UAE because of its\r\nfriendly crypto law. The developers  are from Australia and United Kingdom. They have a plan to launch the OMAX\r\nexchange in early 2023.\r\n\r\n\r\nHow Many OMAX Tokens (OMAX) are there in Circulation?\r\nOMAX has a total supply of 10 billion tokens. 4% of that was already burned. In addition, OMAX follows the patented\r\napproach of deflationary tokens by burning 4% of each\r\ntoken at a BUY&SELL transaction. Doing that, the team\r\nwants to constantly shrink the existing token supply and\r\nincrease the value of OMAX.\r\n\r\n\r\nHow Is the OMAX (OMX 20) Network secured?\r\nOMAX Chain relies on a system of PoS consensus that can support short block time and lower fees. The most bonded validator candidates of staking will become validators and\r\nproduce blocks. The double sign detection and other\r\nslashing logic guarantee security, stability, and chain\r\nfinality. The OMAX Chain also supports EVM-compatible\r\nsmart contracts and protocols. This is the native and only\r\nusable currency in the OMAX ecosystem.","ru":"What Is OMAX TOKEN (OMAX)?\r\nOMAX is a community-driven token which was launched on 3rd of November 2021 in binance network  with the\r\nintention to have its own blockchain to educate the next\r\ngeneration of investors and make crypto simple and safe for everyone.\r\n\r\nOMAX is one of the fastest growing projects which is\r\nmoving from BEP20 to their own network (blockchain\r\nOMX20) which is also a EVM compatible. It is way ahead of the roadmaps and the blockchain is already on testnet and open for public testing with 67K TPS with estimated 85K+\r\nTPS on mainnet. Omax testnet was launched on 3rd of April 2022. OMAX  mainnet is scheduled to launch by the end of\r\nJuly 2022.\r\n\r\nIt further plans to launch a marketing campaign on Twitter\r\nto raise awareness and reach 100,000 holders. That will\r\nlikely go hand in hand with launching of their blockchain.\r\nOMAX was advertised in Times square NY and famous\r\ncelebrities promoted across the globe. Promotion videos\r\ncan be found in the social media.\r\n\r\nWhat Makes OMAX Unique?\r\nIn contrast to many other coins, OMAX promises to feature a complete ecosystem that gives its token real value. Its\r\nblockchain, Ecommerce integration, Crypto card.\r\nBy integrating the Blockchain into popular e-commerce and shopping cart platforms, OMAX aim to grant users the\r\nability to easily complete their everyday purchases using\r\ntheir crypto currency balances.\r\n\r\nOMAX is headquartered in DUBAI, UAE because of its\r\nfriendly crypto law. The developers  are from Australia and United Kingdom. They have a plan to launch the OMAX\r\nexchange in early 2023.\r\n\r\n\r\nHow Many OMAX Tokens (OMAX) are there in Circulation?\r\nOMAX has a total supply of 10 billion tokens. 4% of that was already burned. In addition, OMAX follows the patented\r\napproach of deflationary tokens by burning 4% of each\r\ntoken at a BUY&SELL transaction. Doing that, the team\r\nwants to constantly shrink the existing token supply and\r\nincrease the value of OMAX.\r\n\r\n\r\nHow Is the OMAX (OMX 20) Network secured?\r\nOMAX Chain relies on a system of PoS consensus that can support short block time and lower fees. The most bonded validator candidates of staking will become validators and\r\nproduce blocks. The double sign detection and other\r\nslashing logic guarantee security, stability, and chain\r\nfinality. The OMAX Chain also supports EVM-compatible\r\nsmart contracts and protocols. This is the native and only\r\nusable currency in the OMAX ecosystem.","ja":"What Is OMAX TOKEN (OMAX)?\r\nOMAX is a community-driven token which was launched on 3rd of November 2021 in binance network  with the\r\nintention to have its own blockchain to educate the next\r\ngeneration of investors and make crypto simple and safe for everyone.\r\n\r\nOMAX is one of the fastest growing projects which is\r\nmoving from BEP20 to their own network (blockchain\r\nOMX20) which is also a EVM compatible. It is way ahead of the roadmaps and the blockchain is already on testnet and open for public testing with 67K TPS with estimated 85K+\r\nTPS on mainnet. Omax testnet was launched on 3rd of April 2022. OMAX  mainnet is scheduled to launch by the end of\r\nJuly 2022.\r\n\r\nIt further plans to launch a marketing campaign on Twitter\r\nto raise awareness and reach 100,000 holders. That will\r\nlikely go hand in hand with launching of their blockchain.\r\nOMAX was advertised in Times square NY and famous\r\ncelebrities promoted across the globe. Promotion videos\r\ncan be found in the social media.\r\n\r\nWhat Makes OMAX Unique?\r\nIn contrast to many other coins, OMAX promises to feature a complete ecosystem that gives its token real value. Its\r\nblockchain, Ecommerce integration, Crypto card.\r\nBy integrating the Blockchain into popular e-commerce and shopping cart platforms, OMAX aim to grant users the\r\nability to easily complete their everyday purchases using\r\ntheir crypto currency balances.\r\n\r\nOMAX is headquartered in DUBAI, UAE because of its\r\nfriendly crypto law. The developers  are from Australia and United Kingdom. They have a plan to launch the OMAX\r\nexchange in early 2023.\r\n\r\n\r\nHow Many OMAX Tokens (OMAX) are there in Circulation?\r\nOMAX has a total supply of 10 billion tokens. 4% of that was already burned. In addition, OMAX follows the patented\r\napproach of deflationary tokens by burning 4% of each\r\ntoken at a BUY&SELL transaction. Doing that, the team\r\nwants to constantly shrink the existing token supply and\r\nincrease the value of OMAX.\r\n\r\n\r\nHow Is the OMAX (OMX 20) Network secured?\r\nOMAX Chain relies on a system of PoS consensus that can support short block time and lower fees. The most bonded validator candidates of staking will become validators and\r\nproduce blocks. The double sign detection and other\r\nslashing logic guarantee security, stability, and chain\r\nfinality. The OMAX Chain also supports EVM-compatible\r\nsmart contracts and protocols. This is the native and only\r\nusable currency in the OMAX ecosystem.","zh":"What Is OMAX TOKEN (OMAX)?\r\nOMAX is a community-driven token which was launched on 3rd of November 2021 in binance network  with the\r\nintention to have its own blockchain to educate the next\r\ngeneration of investors and make crypto simple and safe for everyone.\r\n\r\nOMAX is one of the fastest growing projects which is\r\nmoving from BEP20 to their own network (blockchain\r\nOMX20) which is also a EVM compatible. It is way ahead of the roadmaps and the blockchain is already on testnet and open for public testing with 67K TPS with estimated 85K+\r\nTPS on mainnet. Omax testnet was launched on 3rd of April 2022. OMAX  mainnet is scheduled to launch by the end of\r\nJuly 2022.\r\n\r\nIt further plans to launch a marketing campaign on Twitter\r\nto raise awareness and reach 100,000 holders. That will\r\nlikely go hand in hand with launching of their blockchain.\r\nOMAX was advertised in Times square NY and famous\r\ncelebrities promoted across the globe. Promotion videos\r\ncan be found in the social media.\r\n\r\nWhat Makes OMAX Unique?\r\nIn contrast to many other coins, OMAX promises to feature a complete ecosystem that gives its token real value. Its\r\nblockchain, Ecommerce integration, Crypto card.\r\nBy integrating the Blockchain into popular e-commerce and shopping cart platforms, OMAX aim to grant users the\r\nability to easily complete their everyday purchases using\r\ntheir crypto currency balances.\r\n\r\nOMAX is headquartered in DUBAI, UAE because of its\r\nfriendly crypto law. The developers  are from Australia and United Kingdom. They have a plan to launch the OMAX\r\nexchange in early 2023.\r\n\r\n\r\nHow Many OMAX Tokens (OMAX) are there in Circulation?\r\nOMAX has a total supply of 10 billion tokens. 4% of that was already burned. In addition, OMAX follows the patented\r\napproach of deflationary tokens by burning 4% of each\r\ntoken at a BUY&SELL transaction. Doing that, the team\r\nwants to constantly shrink the existing token supply and\r\nincrease the value of OMAX.\r\n\r\n\r\nHow Is the OMAX (OMX 20) Network secured?\r\nOMAX Chain relies on a system of PoS consensus that can support short block time and lower fees. The most bonded validator candidates of staking will become validators and\r\nproduce blocks. The double sign detection and other\r\nslashing logic guarantee security, stability, and chain\r\nfinality. The OMAX Chain also supports EVM-compatible\r\nsmart contracts and protocols. This is the native and only\r\nusable currency in the OMAX ecosystem.","zh-tw":"What Is OMAX TOKEN (OMAX)?\r\nOMAX is a community-driven token which was launched on 3rd of November 2021 in binance network  with the\r\nintention to have its own blockchain to educate the next\r\ngeneration of investors and make crypto simple and safe for everyone.\r\n\r\nOMAX is one of the fastest growing projects which is\r\nmoving from BEP20 to their own network (blockchain\r\nOMX20) which is also a EVM compatible. It is way ahead of the roadmaps and the blockchain is already on testnet and open for public testing with 67K TPS with estimated 85K+\r\nTPS on mainnet. Omax testnet was launched on 3rd of April 2022. OMAX  mainnet is scheduled to launch by the end of\r\nJuly 2022.\r\n\r\nIt further plans to launch a marketing campaign on Twitter\r\nto raise awareness and reach 100,000 holders. That will\r\nlikely go hand in hand with launching of their blockchain.\r\nOMAX was advertised in Times square NY and famous\r\ncelebrities promoted across the globe. Promotion videos\r\ncan be found in the social media.\r\n\r\nWhat Makes OMAX Unique?\r\nIn contrast to many other coins, OMAX promises to feature a complete ecosystem that gives its token real value. Its\r\nblockchain, Ecommerce integration, Crypto card.\r\nBy integrating the Blockchain into popular e-commerce and shopping cart platforms, OMAX aim to grant users the\r\nability to easily complete their everyday purchases using\r\ntheir crypto currency balances.\r\n\r\nOMAX is headquartered in DUBAI, UAE because of its\r\nfriendly crypto law. The developers  are from Australia and United Kingdom. They have a plan to launch the OMAX\r\nexchange in early 2023.\r\n\r\n\r\nHow Many OMAX Tokens (OMAX) are there in Circulation?\r\nOMAX has a total supply of 10 billion tokens. 4% of that was already burned. In addition, OMAX follows the patented\r\napproach of deflationary tokens by burning 4% of each\r\ntoken at a BUY&SELL transaction. Doing that, the team\r\nwants to constantly shrink the existing token supply and\r\nincrease the value of OMAX.\r\n\r\n\r\nHow Is the OMAX (OMX 20) Network secured?\r\nOMAX Chain relies on a system of PoS consensus that can support short block time and lower fees. The most bonded validator candidates of staking will become validators and\r\nproduce blocks. The double sign detection and other\r\nslashing logic guarantee security, stability, and chain\r\nfinality. The OMAX Chain also supports EVM-compatible\r\nsmart contracts and protocols. This is the native and only\r\nusable currency in the OMAX ecosystem.","ko":"What Is OMAX TOKEN (OMAX)?\r\nOMAX is a community-driven token which was launched on 3rd of November 2021 in binance network  with the\r\nintention to have its own blockchain to educate the next\r\ngeneration of investors and make crypto simple and safe for everyone.\r\n\r\nOMAX is one of the fastest growing projects which is\r\nmoving from BEP20 to their own network (blockchain\r\nOMX20) which is also a EVM compatible. It is way ahead of the roadmaps and the blockchain is already on testnet and open for public testing with 67K TPS with estimated 85K+\r\nTPS on mainnet. Omax testnet was launched on 3rd of April 2022. OMAX  mainnet is scheduled to launch by the end of\r\nJuly 2022.\r\n\r\nIt further plans to launch a marketing campaign on Twitter\r\nto raise awareness and reach 100,000 holders. That will\r\nlikely go hand in hand with launching of their blockchain.\r\nOMAX was advertised in Times square NY and famous\r\ncelebrities promoted across the globe. Promotion videos\r\ncan be found in the social media.\r\n\r\nWhat Makes OMAX Unique?\r\nIn contrast to many other coins, OMAX promises to feature a complete ecosystem that gives its token real value. Its\r\nblockchain, Ecommerce integration, Crypto card.\r\nBy integrating the Blockchain into popular e-commerce and shopping cart platforms, OMAX aim to grant users the\r\nability to easily complete their everyday purchases using\r\ntheir crypto currency balances.\r\n\r\nOMAX is headquartered in DUBAI, UAE because of its\r\nfriendly crypto law. The developers  are from Australia and United Kingdom. They have a plan to launch the OMAX\r\nexchange in early 2023.\r\n\r\n\r\nHow Many OMAX Tokens (OMAX) are there in Circulation?\r\nOMAX has a total supply of 10 billion tokens. 4% of that was already burned. In addition, OMAX follows the patented\r\napproach of deflationary tokens by burning 4% of each\r\ntoken at a BUY&SELL transaction. Doing that, the team\r\nwants to constantly shrink the existing token supply and\r\nincrease the value of OMAX.\r\n\r\n\r\nHow Is the OMAX (OMX 20) Network secured?\r\nOMAX Chain relies on a system of PoS consensus that can support short block time and lower fees. The most bonded validator candidates of staking will become validators and\r\nproduce blocks. The double sign detection and other\r\nslashing logic guarantee security, stability, and chain\r\nfinality. The OMAX Chain also supports EVM-compatible\r\nsmart contracts and protocols. This is the native and only\r\nusable currency in the OMAX ecosystem.","ar":"What Is OMAX TOKEN (OMAX)?\r\nOMAX is a community-driven token which was launched on 3rd of November 2021 in binance network  with the\r\nintention to have its own blockchain to educate the next\r\ngeneration of investors and make crypto simple and safe for everyone.\r\n\r\nOMAX is one of the fastest growing projects which is\r\nmoving from BEP20 to their own network (blockchain\r\nOMX20) which is also a EVM compatible. It is way ahead of the roadmaps and the blockchain is already on testnet and open for public testing with 67K TPS with estimated 85K+\r\nTPS on mainnet. Omax testnet was launched on 3rd of April 2022. OMAX  mainnet is scheduled to launch by the end of\r\nJuly 2022.\r\n\r\nIt further plans to launch a marketing campaign on Twitter\r\nto raise awareness and reach 100,000 holders. That will\r\nlikely go hand in hand with launching of their blockchain.\r\nOMAX was advertised in Times square NY and famous\r\ncelebrities promoted across the globe. Promotion videos\r\ncan be found in the social media.\r\n\r\nWhat Makes OMAX Unique?\r\nIn contrast to many other coins, OMAX promises to feature a complete ecosystem that gives its token real value. Its\r\nblockchain, Ecommerce integration, Crypto card.\r\nBy integrating the Blockchain into popular e-commerce and shopping cart platforms, OMAX aim to grant users the\r\nability to easily complete their everyday purchases using\r\ntheir crypto currency balances.\r\n\r\nOMAX is headquartered in DUBAI, UAE because of its\r\nfriendly crypto law. The developers  are from Australia and United Kingdom. They have a plan to launch the OMAX\r\nexchange in early 2023.\r\n\r\n\r\nHow Many OMAX Tokens (OMAX) are there in Circulation?\r\nOMAX has a total supply of 10 billion tokens. 4% of that was already burned. In addition, OMAX follows the patented\r\napproach of deflationary tokens by burning 4% of each\r\ntoken at a BUY&SELL transaction. Doing that, the team\r\nwants to constantly shrink the existing token supply and\r\nincrease the value of OMAX.\r\n\r\n\r\nHow Is the OMAX (OMX 20) Network secured?\r\nOMAX Chain relies on a system of PoS consensus that can support short block time and lower fees. The most bonded validator candidates of staking will become validators and\r\nproduce blocks. The double sign detection and other\r\nslashing logic guarantee security, stability, and chain\r\nfinality. The OMAX Chain also supports EVM-compatible\r\nsmart contracts and protocols. This is the native and only\r\nusable currency in the OMAX ecosystem.","th":"What Is OMAX TOKEN (OMAX)?\r\nOMAX is a community-driven token which was launched on 3rd of November 2021 in binance network  with the\r\nintention to have its own blockchain to educate the next\r\ngeneration of investors and make crypto simple and safe for everyone.\r\n\r\nOMAX is one of the fastest growing projects which is\r\nmoving from BEP20 to their own network (blockchain\r\nOMX20) which is also a EVM compatible. It is way ahead of the roadmaps and the blockchain is already on testnet and open for public testing with 67K TPS with estimated 85K+\r\nTPS on mainnet. Omax testnet was launched on 3rd of April 2022. OMAX  mainnet is scheduled to launch by the end of\r\nJuly 2022.\r\n\r\nIt further plans to launch a marketing campaign on Twitter\r\nto raise awareness and reach 100,000 holders. That will\r\nlikely go hand in hand with launching of their blockchain.\r\nOMAX was advertised in Times square NY and famous\r\ncelebrities promoted across the globe. Promotion videos\r\ncan be found in the social media.\r\n\r\nWhat Makes OMAX Unique?\r\nIn contrast to many other coins, OMAX promises to feature a complete ecosystem that gives its token real value. Its\r\nblockchain, Ecommerce integration, Crypto card.\r\nBy integrating the Blockchain into popular e-commerce and shopping cart platforms, OMAX aim to grant users the\r\nability to easily complete their everyday purchases using\r\ntheir crypto currency balances.\r\n\r\nOMAX is headquartered in DUBAI, UAE because of its\r\nfriendly crypto law. The developers  are from Australia and United Kingdom. They have a plan to launch the OMAX\r\nexchange in early 2023.\r\n\r\n\r\nHow Many OMAX Tokens (OMAX) are there in Circulation?\r\nOMAX has a total supply of 10 billion tokens. 4% of that was already burned. In addition, OMAX follows the patented\r\napproach of deflationary tokens by burning 4% of each\r\ntoken at a BUY&SELL transaction. Doing that, the team\r\nwants to constantly shrink the existing token supply and\r\nincrease the value of OMAX.\r\n\r\n\r\nHow Is the OMAX (OMX 20) Network secured?\r\nOMAX Chain relies on a system of PoS consensus that can support short block time and lower fees. The most bonded validator candidates of staking will become validators and\r\nproduce blocks. The double sign detection and other\r\nslashing logic guarantee security, stability, and chain\r\nfinality. The OMAX Chain also supports EVM-compatible\r\nsmart contracts and protocols. This is the native and only\r\nusable currency in the OMAX ecosystem.","id":"What Is OMAX TOKEN (OMAX)?\r\nOMAX is a community-driven token which was launched on 3rd of November 2021 in binance network  with the\r\nintention to have its own blockchain to educate the next\r\ngeneration of investors and make crypto simple and safe for everyone.\r\n\r\nOMAX is one of the fastest growing projects which is\r\nmoving from BEP20 to their own network (blockchain\r\nOMX20) which is also a EVM compatible. It is way ahead of the roadmaps and the blockchain is already on testnet and open for public testing with 67K TPS with estimated 85K+\r\nTPS on mainnet. Omax testnet was launched on 3rd of April 2022. OMAX  mainnet is scheduled to launch by the end of\r\nJuly 2022.\r\n\r\nIt further plans to launch a marketing campaign on Twitter\r\nto raise awareness and reach 100,000 holders. That will\r\nlikely go hand in hand with launching of their blockchain.\r\nOMAX was advertised in Times square NY and famous\r\ncelebrities promoted across the globe. Promotion videos\r\ncan be found in the social media.\r\n\r\nWhat Makes OMAX Unique?\r\nIn contrast to many other coins, OMAX promises to feature a complete ecosystem that gives its token real value. Its\r\nblockchain, Ecommerce integration, Crypto card.\r\nBy integrating the Blockchain into popular e-commerce and shopping cart platforms, OMAX aim to grant users the\r\nability to easily complete their everyday purchases using\r\ntheir crypto currency balances.\r\n\r\nOMAX is headquartered in DUBAI, UAE because of its\r\nfriendly crypto law. The developers  are from Australia and United Kingdom. They have a plan to launch the OMAX\r\nexchange in early 2023.\r\n\r\n\r\nHow Many OMAX Tokens (OMAX) are there in Circulation?\r\nOMAX has a total supply of 10 billion tokens. 4% of that was already burned. In addition, OMAX follows the patented\r\napproach of deflationary tokens by burning 4% of each\r\ntoken at a BUY&SELL transaction. Doing that, the team\r\nwants to constantly shrink the existing token supply and\r\nincrease the value of OMAX.\r\n\r\n\r\nHow Is the OMAX (OMX 20) Network secured?\r\nOMAX Chain relies on a system of PoS consensus that can support short block time and lower fees. The most bonded validator candidates of staking will become validators and\r\nproduce blocks. The double sign detection and other\r\nslashing logic guarantee security, stability, and chain\r\nfinality. The OMAX Chain also supports EVM-compatible\r\nsmart contracts and protocols. This is the native and only\r\nusable currency in the OMAX ecosystem.","cs":"What Is OMAX TOKEN (OMAX)?\r\nOMAX is a community-driven token which was launched on 3rd of November 2021 in binance network  with the\r\nintention to have its own blockchain to educate the next\r\ngeneration of investors and make crypto simple and safe for everyone.\r\n\r\nOMAX is one of the fastest growing projects which is\r\nmoving from BEP20 to their own network (blockchain\r\nOMX20) which is also a EVM compatible. It is way ahead of the roadmaps and the blockchain is already on testnet and open for public testing with 67K TPS with estimated 85K+\r\nTPS on mainnet. Omax testnet was launched on 3rd of April 2022. OMAX  mainnet is scheduled to launch by the end of\r\nJuly 2022.\r\n\r\nIt further plans to launch a marketing campaign on Twitter\r\nto raise awareness and reach 100,000 holders. That will\r\nlikely go hand in hand with launching of their blockchain.\r\nOMAX was advertised in Times square NY and famous\r\ncelebrities promoted across the globe. Promotion videos\r\ncan be found in the social media.\r\n\r\nWhat Makes OMAX Unique?\r\nIn contrast to many other coins, OMAX promises to feature a complete ecosystem that gives its token real value. Its\r\nblockchain, Ecommerce integration, Crypto card.\r\nBy integrating the Blockchain into popular e-commerce and shopping cart platforms, OMAX aim to grant users the\r\nability to easily complete their everyday purchases using\r\ntheir crypto currency balances.\r\n\r\nOMAX is headquartered in DUBAI, UAE because of its\r\nfriendly crypto law. The developers  are from Australia and United Kingdom. They have a plan to launch the OMAX\r\nexchange in early 2023.\r\n\r\n\r\nHow Many OMAX Tokens (OMAX) are there in Circulation?\r\nOMAX has a total supply of 10 billion tokens. 4% of that was already burned. In addition, OMAX follows the patented\r\napproach of deflationary tokens by burning 4% of each\r\ntoken at a BUY&SELL transaction. Doing that, the team\r\nwants to constantly shrink the existing token supply and\r\nincrease the value of OMAX.\r\n\r\n\r\nHow Is the OMAX (OMX 20) Network secured?\r\nOMAX Chain relies on a system of PoS consensus that can support short block time and lower fees. The most bonded validator candidates of staking will become validators and\r\nproduce blocks. The double sign detection and other\r\nslashing logic guarantee security, stability, and chain\r\nfinality. The OMAX Chain also supports EVM-compatible\r\nsmart contracts and protocols. This is the native and only\r\nusable currency in the OMAX ecosystem.","da":"What Is OMAX TOKEN (OMAX)?\r\nOMAX is a community-driven token which was launched on 3rd of November 2021 in binance network  with the\r\nintention to have its own blockchain to educate the next\r\ngeneration of investors and make crypto simple and safe for everyone.\r\n\r\nOMAX is one of the fastest growing projects which is\r\nmoving from BEP20 to their own network (blockchain\r\nOMX20) which is also a EVM compatible. It is way ahead of the roadmaps and the blockchain is already on testnet and open for public testing with 67K TPS with estimated 85K+\r\nTPS on mainnet. Omax testnet was launched on 3rd of April 2022. OMAX  mainnet is scheduled to launch by the end of\r\nJuly 2022.\r\n\r\nIt further plans to launch a marketing campaign on Twitter\r\nto raise awareness and reach 100,000 holders. That will\r\nlikely go hand in hand with launching of their blockchain.\r\nOMAX was advertised in Times square NY and famous\r\ncelebrities promoted across the globe. Promotion videos\r\ncan be found in the social media.\r\n\r\nWhat Makes OMAX Unique?\r\nIn contrast to many other coins, OMAX promises to feature a complete ecosystem that gives its token real value. Its\r\nblockchain, Ecommerce integration, Crypto card.\r\nBy integrating the Blockchain into popular e-commerce and shopping cart platforms, OMAX aim to grant users the\r\nability to easily complete their everyday purchases using\r\ntheir crypto currency balances.\r\n\r\nOMAX is headquartered in DUBAI, UAE because of its\r\nfriendly crypto law. The developers  are from Australia and United Kingdom. They have a plan to launch the OMAX\r\nexchange in early 2023.\r\n\r\n\r\nHow Many OMAX Tokens (OMAX) are there in Circulation?\r\nOMAX has a total supply of 10 billion tokens. 4% of that was already burned. In addition, OMAX follows the patented\r\napproach of deflationary tokens by burning 4% of each\r\ntoken at a BUY&SELL transaction. Doing that, the team\r\nwants to constantly shrink the existing token supply and\r\nincrease the value of OMAX.\r\n\r\n\r\nHow Is the OMAX (OMX 20) Network secured?\r\nOMAX Chain relies on a system of PoS consensus that can support short block time and lower fees. The most bonded validator candidates of staking will become validators and\r\nproduce blocks. The double sign detection and other\r\nslashing logic guarantee security, stability, and chain\r\nfinality. The OMAX Chain also supports EVM-compatible\r\nsmart contracts and protocols. This is the native and only\r\nusable currency in the OMAX ecosystem.","el":"What Is OMAX TOKEN (OMAX)?\r\nOMAX is a community-driven token which was launched on 3rd of November 2021 in binance network  with the\r\nintention to have its own blockchain to educate the next\r\ngeneration of investors and make crypto simple and safe for everyone.\r\n\r\nOMAX is one of the fastest growing projects which is\r\nmoving from BEP20 to their own network (blockchain\r\nOMX20) which is also a EVM compatible. It is way ahead of the roadmaps and the blockchain is already on testnet and open for public testing with 67K TPS with estimated 85K+\r\nTPS on mainnet. Omax testnet was launched on 3rd of April 2022. OMAX  mainnet is scheduled to launch by the end of\r\nJuly 2022.\r\n\r\nIt further plans to launch a marketing campaign on Twitter\r\nto raise awareness and reach 100,000 holders. That will\r\nlikely go hand in hand with launching of their blockchain.\r\nOMAX was advertised in Times square NY and famous\r\ncelebrities promoted across the globe. Promotion videos\r\ncan be found in the social media.\r\n\r\nWhat Makes OMAX Unique?\r\nIn contrast to many other coins, OMAX promises to feature a complete ecosystem that gives its token real value. Its\r\nblockchain, Ecommerce integration, Crypto card.\r\nBy integrating the Blockchain into popular e-commerce and shopping cart platforms, OMAX aim to grant users the\r\nability to easily complete their everyday purchases using\r\ntheir crypto currency balances.\r\n\r\nOMAX is headquartered in DUBAI, UAE because of its\r\nfriendly crypto law. The developers  are from Australia and United Kingdom. They have a plan to launch the OMAX\r\nexchange in early 2023.\r\n\r\n\r\nHow Many OMAX Tokens (OMAX) are there in Circulation?\r\nOMAX has a total supply of 10 billion tokens. 4% of that was already burned. In addition, OMAX follows the patented\r\napproach of deflationary tokens by burning 4% of each\r\ntoken at a BUY&SELL transaction. Doing that, the team\r\nwants to constantly shrink the existing token supply and\r\nincrease the value of OMAX.\r\n\r\n\r\nHow Is the OMAX (OMX 20) Network secured?\r\nOMAX Chain relies on a system of PoS consensus that can support short block time and lower fees. The most bonded validator candidates of staking will become validators and\r\nproduce blocks. The double sign detection and other\r\nslashing logic guarantee security, stability, and chain\r\nfinality. The OMAX Chain also supports EVM-compatible\r\nsmart contracts and protocols. This is the native and only\r\nusable currency in the OMAX ecosystem.","hi":"What Is OMAX TOKEN (OMAX)?\r\nOMAX is a community-driven token which was launched on 3rd of November 2021 in binance network  with the\r\nintention to have its own blockchain to educate the next\r\ngeneration of investors and make crypto simple and safe for everyone.\r\n\r\nOMAX is one of the fastest growing projects which is\r\nmoving from BEP20 to their own network (blockchain\r\nOMX20) which is also a EVM compatible. It is way ahead of the roadmaps and the blockchain is already on testnet and open for public testing with 67K TPS with estimated 85K+\r\nTPS on mainnet. Omax testnet was launched on 3rd of April 2022. OMAX  mainnet is scheduled to launch by the end of\r\nJuly 2022.\r\n\r\nIt further plans to launch a marketing campaign on Twitter\r\nto raise awareness and reach 100,000 holders. That will\r\nlikely go hand in hand with launching of their blockchain.\r\nOMAX was advertised in Times square NY and famous\r\ncelebrities promoted across the globe. Promotion videos\r\ncan be found in the social media.\r\n\r\nWhat Makes OMAX Unique?\r\nIn contrast to many other coins, OMAX promises to feature a complete ecosystem that gives its token real value. Its\r\nblockchain, Ecommerce integration, Crypto card.\r\nBy integrating the Blockchain into popular e-commerce and shopping cart platforms, OMAX aim to grant users the\r\nability to easily complete their everyday purchases using\r\ntheir crypto currency balances.\r\n\r\nOMAX is headquartered in DUBAI, UAE because of its\r\nfriendly crypto law. The developers  are from Australia and United Kingdom. They have a plan to launch the OMAX\r\nexchange in early 2023.\r\n\r\n\r\nHow Many OMAX Tokens (OMAX) are there in Circulation?\r\nOMAX has a total supply of 10 billion tokens. 4% of that was already burned. In addition, OMAX follows the patented\r\napproach of deflationary tokens by burning 4% of each\r\ntoken at a BUY&SELL transaction. Doing that, the team\r\nwants to constantly shrink the existing token supply and\r\nincrease the value of OMAX.\r\n\r\n\r\nHow Is the OMAX (OMX 20) Network secured?\r\nOMAX Chain relies on a system of PoS consensus that can support short block time and lower fees. The most bonded validator candidates of staking will become validators and\r\nproduce blocks. The double sign detection and other\r\nslashing logic guarantee security, stability, and chain\r\nfinality. The OMAX Chain also supports EVM-compatible\r\nsmart contracts and protocols. This is the native and only\r\nusable currency in the OMAX ecosystem.","no":"What Is OMAX TOKEN (OMAX)?\r\nOMAX is a community-driven token which was launched on 3rd of November 2021 in binance network  with the\r\nintention to have its own blockchain to educate the next\r\ngeneration of investors and make crypto simple and safe for everyone.\r\n\r\nOMAX is one of the fastest growing projects which is\r\nmoving from BEP20 to their own network (blockchain\r\nOMX20) which is also a EVM compatible. It is way ahead of the roadmaps and the blockchain is already on testnet and open for public testing with 67K TPS with estimated 85K+\r\nTPS on mainnet. Omax testnet was launched on 3rd of April 2022. OMAX  mainnet is scheduled to launch by the end of\r\nJuly 2022.\r\n\r\nIt further plans to launch a marketing campaign on Twitter\r\nto raise awareness and reach 100,000 holders. That will\r\nlikely go hand in hand with launching of their blockchain.\r\nOMAX was advertised in Times square NY and famous\r\ncelebrities promoted across the globe. Promotion videos\r\ncan be found in the social media.\r\n\r\nWhat Makes OMAX Unique?\r\nIn contrast to many other coins, OMAX promises to feature a complete ecosystem that gives its token real value. Its\r\nblockchain, Ecommerce integration, Crypto card.\r\nBy integrating the Blockchain into popular e-commerce and shopping cart platforms, OMAX aim to grant users the\r\nability to easily complete their everyday purchases using\r\ntheir crypto currency balances.\r\n\r\nOMAX is headquartered in DUBAI, UAE because of its\r\nfriendly crypto law. The developers  are from Australia and United Kingdom. They have a plan to launch the OMAX\r\nexchange in early 2023.\r\n\r\n\r\nHow Many OMAX Tokens (OMAX) are there in Circulation?\r\nOMAX has a total supply of 10 billion tokens. 4% of that was already burned. In addition, OMAX follows the patented\r\napproach of deflationary tokens by burning 4% of each\r\ntoken at a BUY&SELL transaction. Doing that, the team\r\nwants to constantly shrink the existing token supply and\r\nincrease the value of OMAX.\r\n\r\n\r\nHow Is the OMAX (OMX 20) Network secured?\r\nOMAX Chain relies on a system of PoS consensus that can support short block time and lower fees. The most bonded validator candidates of staking will become validators and\r\nproduce blocks. The double sign detection and other\r\nslashing logic guarantee security, stability, and chain\r\nfinality. The OMAX Chain also supports EVM-compatible\r\nsmart contracts and protocols. This is the native and only\r\nusable currency in the OMAX ecosystem.","sk":"What Is OMAX TOKEN (OMAX)?\r\nOMAX is a community-driven token which was launched on 3rd of November 2021 in binance network  with the\r\nintention to have its own blockchain to educate the next\r\ngeneration of investors and make crypto simple and safe for everyone.\r\n\r\nOMAX is one of the fastest growing projects which is\r\nmoving from BEP20 to their own network (blockchain\r\nOMX20) which is also a EVM compatible. It is way ahead of the roadmaps and the blockchain is already on testnet and open for public testing with 67K TPS with estimated 85K+\r\nTPS on mainnet. Omax testnet was launched on 3rd of April 2022. OMAX  mainnet is scheduled to launch by the end of\r\nJuly 2022.\r\n\r\nIt further plans to launch a marketing campaign on Twitter\r\nto raise awareness and reach 100,000 holders. That will\r\nlikely go hand in hand with launching of their blockchain.\r\nOMAX was advertised in Times square NY and famous\r\ncelebrities promoted across the globe. Promotion videos\r\ncan be found in the social media.\r\n\r\nWhat Makes OMAX Unique?\r\nIn contrast to many other coins, OMAX promises to feature a complete ecosystem that gives its token real value. Its\r\nblockchain, Ecommerce integration, Crypto card.\r\nBy integrating the Blockchain into popular e-commerce and shopping cart platforms, OMAX aim to grant users the\r\nability to easily complete their everyday purchases using\r\ntheir crypto currency balances.\r\n\r\nOMAX is headquartered in DUBAI, UAE because of its\r\nfriendly crypto law. The developers  are from Australia and United Kingdom. They have a plan to launch the OMAX\r\nexchange in early 2023.\r\n\r\n\r\nHow Many OMAX Tokens (OMAX) are there in Circulation?\r\nOMAX has a total supply of 10 billion tokens. 4% of that was already burned. In addition, OMAX follows the patented\r\napproach of deflationary tokens by burning 4% of each\r\ntoken at a BUY&SELL transaction. Doing that, the team\r\nwants to constantly shrink the existing token supply and\r\nincrease the value of OMAX.\r\n\r\n\r\nHow Is the OMAX (OMX 20) Network secured?\r\nOMAX Chain relies on a system of PoS consensus that can support short block time and lower fees. The most bonded validator candidates of staking will become validators and\r\nproduce blocks. The double sign detection and other\r\nslashing logic guarantee security, stability, and chain\r\nfinality. The OMAX Chain also supports EVM-compatible\r\nsmart contracts and protocols. This is the native and only\r\nusable currency in the OMAX ecosystem.","uk":"What Is OMAX TOKEN (OMAX)?\r\nOMAX is a community-driven token which was launched on 3rd of November 2021 in binance network  with the\r\nintention to have its own blockchain to educate the next\r\ngeneration of investors and make crypto simple and safe for everyone.\r\n\r\nOMAX is one of the fastest growing projects which is\r\nmoving from BEP20 to their own network (blockchain\r\nOMX20) which is also a EVM compatible. It is way ahead of the roadmaps and the blockchain is already on testnet and open for public testing with 67K TPS with estimated 85K+\r\nTPS on mainnet. Omax testnet was launched on 3rd of April 2022. OMAX  mainnet is scheduled to launch by the end of\r\nJuly 2022.\r\n\r\nIt further plans to launch a marketing campaign on Twitter\r\nto raise awareness and reach 100,000 holders. That will\r\nlikely go hand in hand with launching of their blockchain.\r\nOMAX was advertised in Times square NY and famous\r\ncelebrities promoted across the globe. Promotion videos\r\ncan be found in the social media.\r\n\r\nWhat Makes OMAX Unique?\r\nIn contrast to many other coins, OMAX promises to feature a complete ecosystem that gives its token real value. Its\r\nblockchain, Ecommerce integration, Crypto card.\r\nBy integrating the Blockchain into popular e-commerce and shopping cart platforms, OMAX aim to grant users the\r\nability to easily complete their everyday purchases using\r\ntheir crypto currency balances.\r\n\r\nOMAX is headquartered in DUBAI, UAE because of its\r\nfriendly crypto law. The developers  are from Australia and United Kingdom. They have a plan to launch the OMAX\r\nexchange in early 2023.\r\n\r\n\r\nHow Many OMAX Tokens (OMAX) are there in Circulation?\r\nOMAX has a total supply of 10 billion tokens. 4% of that was already burned. In addition, OMAX follows the patented\r\napproach of deflationary tokens by burning 4% of each\r\ntoken at a BUY&SELL transaction. Doing that, the team\r\nwants to constantly shrink the existing token supply and\r\nincrease the value of OMAX.\r\n\r\n\r\nHow Is the OMAX (OMX 20) Network secured?\r\nOMAX Chain relies on a system of PoS consensus that can support short block time and lower fees. The most bonded validator candidates of staking will become validators and\r\nproduce blocks. The double sign detection and other\r\nslashing logic guarantee security, stability, and chain\r\nfinality. The OMAX Chain also supports EVM-compatible\r\nsmart contracts and protocols. This is the native and only\r\nusable currency in the OMAX ecosystem.","he":"What Is OMAX TOKEN (OMAX)?\r\nOMAX is a community-driven token which was launched on 3rd of November 2021 in binance network  with the\r\nintention to have its own blockchain to educate the next\r\ngeneration of investors and make crypto simple and safe for everyone.\r\n\r\nOMAX is one of the fastest growing projects which is\r\nmoving from BEP20 to their own network (blockchain\r\nOMX20) which is also a EVM compatible. It is way ahead of the roadmaps and the blockchain is already on testnet and open for public testing with 67K TPS with estimated 85K+\r\nTPS on mainnet. Omax testnet was launched on 3rd of April 2022. OMAX  mainnet is scheduled to launch by the end of\r\nJuly 2022.\r\n\r\nIt further plans to launch a marketing campaign on Twitter\r\nto raise awareness and reach 100,000 holders. That will\r\nlikely go hand in hand with launching of their blockchain.\r\nOMAX was advertised in Times square NY and famous\r\ncelebrities promoted across the globe. Promotion videos\r\ncan be found in the social media.\r\n\r\nWhat Makes OMAX Unique?\r\nIn contrast to many other coins, OMAX promises to feature a complete ecosystem that gives its token real value. Its\r\nblockchain, Ecommerce integration, Crypto card.\r\nBy integrating the Blockchain into popular e-commerce and shopping cart platforms, OMAX aim to grant users the\r\nability to easily complete their everyday purchases using\r\ntheir crypto currency balances.\r\n\r\nOMAX is headquartered in DUBAI, UAE because of its\r\nfriendly crypto law. The developers  are from Australia and United Kingdom. They have a plan to launch the OMAX\r\nexchange in early 2023.\r\n\r\n\r\nHow Many OMAX Tokens (OMAX) are there in Circulation?\r\nOMAX has a total supply of 10 billion tokens. 4% of that was already burned. In addition, OMAX follows the patented\r\napproach of deflationary tokens by burning 4% of each\r\ntoken at a BUY&SELL transaction. Doing that, the team\r\nwants to constantly shrink the existing token supply and\r\nincrease the value of OMAX.\r\n\r\n\r\nHow Is the OMAX (OMX 20) Network secured?\r\nOMAX Chain relies on a system of PoS consensus that can support short block time and lower fees. The most bonded validator candidates of staking will become validators and\r\nproduce blocks. The double sign detection and other\r\nslashing logic guarantee security, stability, and chain\r\nfinality. The OMAX Chain also supports EVM-compatible\r\nsmart contracts and protocols. This is the native and only\r\nusable currency in the OMAX ecosystem.","fi":"What Is OMAX TOKEN (OMAX)?\r\nOMAX is a community-driven token which was launched on 3rd of November 2021 in binance network  with the\r\nintention to have its own blockchain to educate the next\r\ngeneration of investors and make crypto simple and safe for everyone.\r\n\r\nOMAX is one of the fastest growing projects which is\r\nmoving from BEP20 to their own network (blockchain\r\nOMX20) which is also a EVM compatible. It is way ahead of the roadmaps and the blockchain is already on testnet and open for public testing with 67K TPS with estimated 85K+\r\nTPS on mainnet. Omax testnet was launched on 3rd of April 2022. OMAX  mainnet is scheduled to launch by the end of\r\nJuly 2022.\r\n\r\nIt further plans to launch a marketing campaign on Twitter\r\nto raise awareness and reach 100,000 holders. That will\r\nlikely go hand in hand with launching of their blockchain.\r\nOMAX was advertised in Times square NY and famous\r\ncelebrities promoted across the globe. Promotion videos\r\ncan be found in the social media.\r\n\r\nWhat Makes OMAX Unique?\r\nIn contrast to many other coins, OMAX promises to feature a complete ecosystem that gives its token real value. Its\r\nblockchain, Ecommerce integration, Crypto card.\r\nBy integrating the Blockchain into popular e-commerce and shopping cart platforms, OMAX aim to grant users the\r\nability to easily complete their everyday purchases using\r\ntheir crypto currency balances.\r\n\r\nOMAX is headquartered in DUBAI, UAE because of its\r\nfriendly crypto law. The developers  are from Australia and United Kingdom. They have a plan to launch the OMAX\r\nexchange in early 2023.\r\n\r\n\r\nHow Many OMAX Tokens (OMAX) are there in Circulation?\r\nOMAX has a total supply of 10 billion tokens. 4% of that was already burned. In addition, OMAX follows the patented\r\napproach of deflationary tokens by burning 4% of each\r\ntoken at a BUY&SELL transaction. Doing that, the team\r\nwants to constantly shrink the existing token supply and\r\nincrease the value of OMAX.\r\n\r\n\r\nHow Is the OMAX (OMX 20) Network secured?\r\nOMAX Chain relies on a system of PoS consensus that can support short block time and lower fees. The most bonded validator candidates of staking will become validators and\r\nproduce blocks. The double sign detection and other\r\nslashing logic guarantee security, stability, and chain\r\nfinality. The OMAX Chain also supports EVM-compatible\r\nsmart contracts and protocols. This is the native and only\r\nusable currency in the OMAX ecosystem.","bg":"What Is OMAX TOKEN (OMAX)?\r\nOMAX is a community-driven token which was launched on 3rd of November 2021 in binance network  with the\r\nintention to have its own blockchain to educate the next\r\ngeneration of investors and make crypto simple and safe for everyone.\r\n\r\nOMAX is one of the fastest growing projects which is\r\nmoving from BEP20 to their own network (blockchain\r\nOMX20) which is also a EVM compatible. It is way ahead of the roadmaps and the blockchain is already on testnet and open for public testing with 67K TPS with estimated 85K+\r\nTPS on mainnet. Omax testnet was launched on 3rd of April 2022. OMAX  mainnet is scheduled to launch by the end of\r\nJuly 2022.\r\n\r\nIt further plans to launch a marketing campaign on Twitter\r\nto raise awareness and reach 100,000 holders. That will\r\nlikely go hand in hand with launching of their blockchain.\r\nOMAX was advertised in Times square NY and famous\r\ncelebrities promoted across the globe. Promotion videos\r\ncan be found in the social media.\r\n\r\nWhat Makes OMAX Unique?\r\nIn contrast to many other coins, OMAX promises to feature a complete ecosystem that gives its token real value. Its\r\nblockchain, Ecommerce integration, Crypto card.\r\nBy integrating the Blockchain into popular e-commerce and shopping cart platforms, OMAX aim to grant users the\r\nability to easily complete their everyday purchases using\r\ntheir crypto currency balances.\r\n\r\nOMAX is headquartered in DUBAI, UAE because of its\r\nfriendly crypto law. The developers  are from Australia and United Kingdom. They have a plan to launch the OMAX\r\nexchange in early 2023.\r\n\r\n\r\nHow Many OMAX Tokens (OMAX) are there in Circulation?\r\nOMAX has a total supply of 10 billion tokens. 4% of that was already burned. In addition, OMAX follows the patented\r\napproach of deflationary tokens by burning 4% of each\r\ntoken at a BUY&SELL transaction. Doing that, the team\r\nwants to constantly shrink the existing token supply and\r\nincrease the value of OMAX.\r\n\r\n\r\nHow Is the OMAX (OMX 20) Network secured?\r\nOMAX Chain relies on a system of PoS consensus that can support short block time and lower fees. The most bonded validator candidates of staking will become validators and\r\nproduce blocks. The double sign detection and other\r\nslashing logic guarantee security, stability, and chain\r\nfinality. The OMAX Chain also supports EVM-compatible\r\nsmart contracts and protocols. This is the native and only\r\nusable currency in the OMAX ecosystem.","hr":"What Is OMAX TOKEN (OMAX)?\r\nOMAX is a community-driven token which was launched on 3rd of November 2021 in binance network  with the\r\nintention to have its own blockchain to educate the next\r\ngeneration of investors and make crypto simple and safe for everyone.\r\n\r\nOMAX is one of the fastest growing projects which is\r\nmoving from BEP20 to their own network (blockchain\r\nOMX20) which is also a EVM compatible. It is way ahead of the roadmaps and the blockchain is already on testnet and open for public testing with 67K TPS with estimated 85K+\r\nTPS on mainnet. Omax testnet was launched on 3rd of April 2022. OMAX  mainnet is scheduled to launch by the end of\r\nJuly 2022.\r\n\r\nIt further plans to launch a marketing campaign on Twitter\r\nto raise awareness and reach 100,000 holders. That will\r\nlikely go hand in hand with launching of their blockchain.\r\nOMAX was advertised in Times square NY and famous\r\ncelebrities promoted across the globe. Promotion videos\r\ncan be found in the social media.\r\n\r\nWhat Makes OMAX Unique?\r\nIn contrast to many other coins, OMAX promises to feature a complete ecosystem that gives its token real value. Its\r\nblockchain, Ecommerce integration, Crypto card.\r\nBy integrating the Blockchain into popular e-commerce and shopping cart platforms, OMAX aim to grant users the\r\nability to easily complete their everyday purchases using\r\ntheir crypto currency balances.\r\n\r\nOMAX is headquartered in DUBAI, UAE because of its\r\nfriendly crypto law. The developers  are from Australia and United Kingdom. They have a plan to launch the OMAX\r\nexchange in early 2023.\r\n\r\n\r\nHow Many OMAX Tokens (OMAX) are there in Circulation?\r\nOMAX has a total supply of 10 billion tokens. 4% of that was already burned. In addition, OMAX follows the patented\r\napproach of deflationary tokens by burning 4% of each\r\ntoken at a BUY&SELL transaction. Doing that, the team\r\nwants to constantly shrink the existing token supply and\r\nincrease the value of OMAX.\r\n\r\n\r\nHow Is the OMAX (OMX 20) Network secured?\r\nOMAX Chain relies on a system of PoS consensus that can support short block time and lower fees. The most bonded validator candidates of staking will become validators and\r\nproduce blocks. The double sign detection and other\r\nslashing logic guarantee security, stability, and chain\r\nfinality. The OMAX Chain also supports EVM-compatible\r\nsmart contracts and protocols. This is the native and only\r\nusable currency in the OMAX ecosystem.","lt":"What Is OMAX TOKEN (OMAX)?\r\nOMAX is a community-driven token which was launched on 3rd of November 2021 in binance network  with the\r\nintention to have its own blockchain to educate the next\r\ngeneration of investors and make crypto simple and safe for everyone.\r\n\r\nOMAX is one of the fastest growing projects which is\r\nmoving from BEP20 to their own network (blockchain\r\nOMX20) which is also a EVM compatible. It is way ahead of the roadmaps and the blockchain is already on testnet and open for public testing with 67K TPS with estimated 85K+\r\nTPS on mainnet. Omax testnet was launched on 3rd of April 2022. OMAX  mainnet is scheduled to launch by the end of\r\nJuly 2022.\r\n\r\nIt further plans to launch a marketing campaign on Twitter\r\nto raise awareness and reach 100,000 holders. That will\r\nlikely go hand in hand with launching of their blockchain.\r\nOMAX was advertised in Times square NY and famous\r\ncelebrities promoted across the globe. Promotion videos\r\ncan be found in the social media.\r\n\r\nWhat Makes OMAX Unique?\r\nIn contrast to many other coins, OMAX promises to feature a complete ecosystem that gives its token real value. Its\r\nblockchain, Ecommerce integration, Crypto card.\r\nBy integrating the Blockchain into popular e-commerce and shopping cart platforms, OMAX aim to grant users the\r\nability to easily complete their everyday purchases using\r\ntheir crypto currency balances.\r\n\r\nOMAX is headquartered in DUBAI, UAE because of its\r\nfriendly crypto law. The developers  are from Australia and United Kingdom. They have a plan to launch the OMAX\r\nexchange in early 2023.\r\n\r\n\r\nHow Many OMAX Tokens (OMAX) are there in Circulation?\r\nOMAX has a total supply of 10 billion tokens. 4% of that was already burned. In addition, OMAX follows the patented\r\napproach of deflationary tokens by burning 4% of each\r\ntoken at a BUY&SELL transaction. Doing that, the team\r\nwants to constantly shrink the existing token supply and\r\nincrease the value of OMAX.\r\n\r\n\r\nHow Is the OMAX (OMX 20) Network secured?\r\nOMAX Chain relies on a system of PoS consensus that can support short block time and lower fees. The most bonded validator candidates of staking will become validators and\r\nproduce blocks. The double sign detection and other\r\nslashing logic guarantee security, stability, and chain\r\nfinality. The OMAX Chain also supports EVM-compatible\r\nsmart contracts and protocols. This is the native and only\r\nusable currency in the OMAX ecosystem.","sl":"What Is OMAX TOKEN (OMAX)?\r\nOMAX is a community-driven token which was launched on 3rd of November 2021 in binance network  with the\r\nintention to have its own blockchain to educate the next\r\ngeneration of investors and make crypto simple and safe for everyone.\r\n\r\nOMAX is one of the fastest growing projects which is\r\nmoving from BEP20 to their own network (blockchain\r\nOMX20) which is also a EVM compatible. It is way ahead of the roadmaps and the blockchain is already on testnet and open for public testing with 67K TPS with estimated 85K+\r\nTPS on mainnet. Omax testnet was launched on 3rd of April 2022. OMAX  mainnet is scheduled to launch by the end of\r\nJuly 2022.\r\n\r\nIt further plans to launch a marketing campaign on Twitter\r\nto raise awareness and reach 100,000 holders. That will\r\nlikely go hand in hand with launching of their blockchain.\r\nOMAX was advertised in Times square NY and famous\r\ncelebrities promoted across the globe. Promotion videos\r\ncan be found in the social media.\r\n\r\nWhat Makes OMAX Unique?\r\nIn contrast to many other coins, OMAX promises to feature a complete ecosystem that gives its token real value. Its\r\nblockchain, Ecommerce integration, Crypto card.\r\nBy integrating the Blockchain into popular e-commerce and shopping cart platforms, OMAX aim to grant users the\r\nability to easily complete their everyday purchases using\r\ntheir crypto currency balances.\r\n\r\nOMAX is headquartered in DUBAI, UAE because of its\r\nfriendly crypto law. The developers  are from Australia and United Kingdom. They have a plan to launch the OMAX\r\nexchange in early 2023.\r\n\r\n\r\nHow Many OMAX Tokens (OMAX) are there in Circulation?\r\nOMAX has a total supply of 10 billion tokens. 4% of that was already burned. In addition, OMAX follows the patented\r\napproach of deflationary tokens by burning 4% of each\r\ntoken at a BUY&SELL transaction. Doing that, the team\r\nwants to constantly shrink the existing token supply and\r\nincrease the value of OMAX.\r\n\r\n\r\nHow Is the OMAX (OMX 20) Network secured?\r\nOMAX Chain relies on a system of PoS consensus that can support short block time and lower fees. The most bonded validator candidates of staking will become validators and\r\nproduce blocks. The double sign detection and other\r\nslashing logic guarantee security, stability, and chain\r\nfinality. The OMAX Chain also supports EVM-compatible\r\nsmart contracts and protocols. This is the native and only\r\nusable currency in the OMAX ecosystem."},"links":{"homepage":["https://omaxcoin.com/","",""],"blockchain_site":["https://omaxray.com/","","","","","","","","",""],"official_forum_url":["","",""],"chat_url":["","",""],"announcement_url":["",""],"twitter_screen_name":"omaxtoken","facebook_username":"","bitcointalk_thread_identifier":null,"telegram_channel_identifier":"OmaxToken","subreddit_url":null,"repos_url":{"github":[],"bitbucket":[]}},"image":{"thumb":"https://assets.coingecko.com/coins/images/19853/thumb/omxlogo.png?1636061849","small":"https://assets.coingecko.com/coins/images/19853/small/omxlogo.png?1636061849","large":"https://assets.coingecko.com/coins/images/19853/large/omxlogo.png?1636061849"},"country_origin":"","genesis_date":null,"sentiment_votes_up_percentage":66.67,"sentiment_votes_down_percentage":33.33,"watchlist_portfolio_users":13703,"market_cap_rank":1293,"coingecko_rank":1209,"coingecko_score":19.71,"developer_score":0,"community_score":8.323,"liquidity_score":27.751,"public_interest_score":0.001,"public_interest_stats":{"alexa_rank":null,"bing_matches":null},"status_updates":[],"last_updated":"2023-07-14T02:25:46.207Z"}